logicossoftware_mdocx-0.1.0.dist-info/licenses/LICENSE
pymdocx/__init__.py
pymdocx/compression.py
pymdocx/constants.py
pymdocx/gob.py
pymdocx/models.py
pymdocx/reader.py
pymdocx/writer.py
logicossoftware_mdocx-0.1.0.dist-info/METADATA
logicossoftware_mdocx-0.1.0.dist-info/WHEEL
logicossoftware_mdocx-0.1.0.dist-info/top_level.txt
logicossoftware_mdocx-0.1.0.dist-info/RECORD
