Metadata-Version: 2.4
Name: logicossoftware-mdocx
Version: 0.1.0
Summary: Python implementation of the MDOCX (MarkDown Open Container eXchange) file format
Author: MHJ Wiggers
License: MIT
Project-URL: Homepage, https://github.com/logicossoftware/py-mdocx
Project-URL: Bug Tracker, https://github.com/logicossoftware/py-mdocx/issues
Keywords: markdown,container,mdocx,document,media,bundle
Classifier: Development Status :: 3 - Alpha
Classifier: Intended Audience :: Developers
Classifier: License :: OSI Approved :: MIT License
Classifier: Operating System :: OS Independent
Classifier: Programming Language :: Python :: 3
Classifier: Programming Language :: Python :: 3.10
Classifier: Programming Language :: Python :: 3.11
Classifier: Programming Language :: Python :: 3.12
Classifier: Topic :: Text Processing :: Markup :: Markdown
Classifier: Topic :: File Formats
Requires-Python: >=3.10
License-File: LICENSE
Provides-Extra: zstd
Requires-Dist: zstandard>=0.21.0; extra == "zstd"
Provides-Extra: lz4
Requires-Dist: lz4>=4.3.0; extra == "lz4"
Provides-Extra: brotli
Requires-Dist: brotli>=1.1.0; extra == "brotli"
Provides-Extra: all
Requires-Dist: zstandard>=0.21.0; extra == "all"
Requires-Dist: lz4>=4.3.0; extra == "all"
Requires-Dist: brotli>=1.1.0; extra == "all"
Provides-Extra: dev
Requires-Dist: pytest>=7.0.0; extra == "dev"
Requires-Dist: pytest-cov>=4.0.0; extra == "dev"
Requires-Dist: zstandard>=0.21.0; extra == "dev"
Requires-Dist: lz4>=4.3.0; extra == "dev"
Requires-Dist: brotli>=1.1.0; extra == "dev"
Dynamic: license-file
